{
  "deleted": false,
  "DATA": 4,
  "INFO": {
    "575543361036629602": {
      "flag": 0,
      "PNAM": "20722124852575822469",
      "NNAM": "",
      "DATA": {
        "value": 1,
        "rank": -1,
        "gender": -1,
        "player_rank": -1
      },
      "ONAM": null,
      "RNAM": null,
      "CNAM": null,
      "FNAM": null,
      "ANAM": null,
      "DNAM": null,
      "SNAM": null,
      "NAME": "I spoke with Vireveri Darethran who had been driven mad by dreams of Dagoth Ur and the Sixth House. This former 'Sleeper' thanked me, and promised to tell others how I had saved her life.",
      "BNAM": null,
      "SCVR": null
    },
    "20722124852575822469": {
      "flag": 2,
      "PNAM": "",
      "NNAM": "575543361036629602",
      "DATA": {
        "value": 0,
        "rank": -1,
        "gender": -1,
        "player_rank": -1
      },
      "ONAM": null,
      "RNAM": null,
      "CNAM": null,
      "FNAM": null,
      "ANAM": null,
      "DNAM": null,
      "SNAM": null,
      "NAME": "Sleepers Awake",
      "BNAM": null,
      "SCVR": null
    }
  }
}