{
  "deleted": false,
  "DATA": 1,
  "NNAM": 5,
  "INAM": [
    {
      "name": "orcish_boots",
      "pc_level": 1
    },
    {
      "name": "orcish_bracer_left",
      "pc_level": 1
    },
    {
      "name": "orcish_bracer_right",
      "pc_level": 1
    },
    {
      "name": "orcish_cuirass",
      "pc_level": 1
    },
    {
      "name": "orcish_greaves",
      "pc_level": 1
    },
    {
      "name": "orcish_helm",
      "pc_level": 1
    },
    {
      "name": "orcish_pauldron_left",
      "pc_level": 1
    },
    {
      "name": "orcish_pauldron_right",
      "pc_level": 1
    },
    {
      "name": "orcish_towershield",
      "pc_level": 1
    }
  ]
}