{
  "deleted": false,
  "DATA": {
    "flags": 5,
    "grid": [2702672,1061158912]
  },
  "NAME": "Vivec, Redoran Records",
  "RGNN": null,
  "WHGT": null,
  "NAM5": null,
  "AMBI": {
    "ambient": [67,61,54,0],
    "sunlight": [67,40,14,0],
    "fog_color": [80,61,41,0],
    "fog_density": 0.75
  },
  "FRMR": {
    "0-241873": {
      "deleted": false,
      "persistent": true,
      "initially_disabled": false,
      "blocked": false,
      "NAME": "hlavora sadas",
      "DATA": [49.48676300048828,-238.608154296875,-87.59886932373047,0,0,0]
    },
    "0-241874": {
      "deleted": false,
      "persistent": true,
      "initially_disabled": false,
      "blocked": false,
      "NAME": "rathyne thirano",
      "DATA": [-136.97860717773438,-212.64105224609375,-89.93424987792969,0,0,0]
    },
    "0-188353": {
      "deleted": false,
      "persistent": true,
      "initially_disabled": false,
      "blocked": false,
      "NAME": "in_velothismall_ndoor_01",
      "DATA": [-64,128,-128,0,0,4.71238899230957]
    },
    "0-188362": {
      "deleted": false,
      "persistent": false,
      "initially_disabled": false,
      "blocked": false,
      "NAME": "de_p_desk_01_pos",
      "ANAM": "rathyne thirano",
      "INTV": 0,
      "NAM9": 1,
      "DATA": [212.18499755859375,-200.93499755859375,-75.31700134277344,0,0,6.2831854820251465]
    },
    "0-188363": {
      "deleted": false,
      "persistent": false,
      "initially_disabled": false,
      "blocked": false,
      "NAME": "de_p_desk_01_pos",
      "ANAM": "rathyne thirano",
      "INTV": 0,
      "NAM9": 1,
      "DATA": [-258.6017150878906,-201.74227905273438,-75.31732177734375,0,0,6.2831854820251465]
    },
    "0-241876": {
      "deleted": false,
      "persistent": false,
      "initially_disabled": false,
      "blocked": false,
      "NAME": "light_de_lamp_04",
      "DATA": [-733.4024658203125,-203.65585327148438,8.387866973876953,0,0,5.433185577392578]
    },
    "0-241882": {
      "deleted": false,
      "persistent": false,
      "initially_disabled": false,
      "blocked": false,
      "NAME": "light_de_candle_07_64",
      "DATA": [289.0924987792969,37.82101058959961,-49.29087448120117,0,0,0]
    },
    "0-241883": {
      "deleted": false,
      "persistent": false,
      "initially_disabled": false,
      "blocked": false,
      "NAME": "light_de_candle_08_64",
      "DATA": [257.9355163574219,-206.65835571289062,-38.53340530395508,0,0,0]
    },
    "0-241884": {
      "deleted": false,
      "persistent": false,
      "initially_disabled": false,
      "blocked": false,
      "NAME": "light_de_candle_08_64",
      "DATA": [-303.6476745605469,-204.83245849609375,-39.10124588012695,0,0,0]
    },
    "0-188337": {
      "deleted": false,
      "persistent": false,
      "initially_disabled": false,
      "blocked": false,
      "NAME": "in_v_s_int_entrance_01",
      "DATA": [0,0,0,0,0,1.5707963705062866]
    },
    "0-188338": {
      "deleted": false,
      "persistent": false,
      "initially_disabled": false,
      "blocked": false,
      "NAME": "in_v_s_int_corner_01",
      "DATA": [256,0,0,0,0,6.2831854820251465]
    },
    "0-188339": {
      "deleted": false,
      "persistent": false,
      "initially_disabled": false,
      "blocked": false,
      "NAME": "in_v_s_int_corner_01",
      "DATA": [-256.00048828125,0,0,0,0,4.71238899230957]
    },
    "0-188342": {
      "deleted": false,
      "persistent": false,
      "initially_disabled": false,
      "blocked": false,
      "NAME": "in_velothismall_hall_03",
      "DATA": [-256,-512,0,0,0,1.5707963705062866]
    },
    "0-188343": {
      "deleted": false,
      "persistent": false,
      "initially_disabled": false,
      "blocked": false,
      "NAME": "in_v_s_int_entrance_01",
      "DATA": [0,-256,0,0,0,4.71238899230957]
    },
    "0-188345": {
      "deleted": false,
      "persistent": false,
      "initially_disabled": false,
      "blocked": false,
      "NAME": "in_v_s_int_wall_01",
      "DATA": [-256,-256,0,0,0,0]
    },
    "0-188346": {
      "deleted": false,
      "persistent": false,
      "initially_disabled": false,
      "blocked": false,
      "NAME": "in_v_s_int_corner_01",
      "DATA": [256,-256,0,0,0,1.5707963705062866]
    },
    "0-188347": {
      "deleted": false,
      "persistent": false,
      "initially_disabled": false,
      "blocked": false,
      "NAME": "in_v_s_int_corner_01",
      "DATA": [-768.0000610351562,-511.99993896484375,0,0,0,3.141592264175415]
    },
    "0-188348": {
      "deleted": false,
      "persistent": false,
      "initially_disabled": false,
      "blocked": false,
      "NAME": "in_v_s_int_corner_01",
      "DATA": [-767.9999389648438,-256.00006103515625,0,0,0,4.71238899230957]
    },
    "0-188349": {
      "deleted": false,
      "persistent": false,
      "initially_disabled": false,
      "blocked": false,
      "NAME": "in_v_s_int_corner_01",
      "DATA": [-512,-256,0,0,0,6.283185005187988]
    },
    "0-188350": {
      "deleted": false,
      "persistent": false,
      "initially_disabled": false,
      "blocked": false,
      "NAME": "in_v_s_wall_column_02",
      "DATA": [-512,-512,0,0,0,1.5707963705062866]
    },
    "0-188351": {
      "deleted": false,
      "persistent": false,
      "initially_disabled": false,
      "blocked": false,
      "NAME": "in_velothismall_corner_01",
      "DATA": [0,-512,0,0,0,1.5707963705062866]
    },
    "0-188352": {
      "deleted": false,
      "persistent": false,
      "initially_disabled": false,
      "blocked": false,
      "NAME": "in_velothismall_dj_01",
      "DATA": [0,128,-128,0,0,1.5707963705062866]
    },
    "0-188355": {
      "deleted": false,
      "persistent": false,
      "initially_disabled": false,
      "blocked": false,
      "NAME": "in_velothismall_dj_01",
      "DATA": [0.000030517578125,-384.00006103515625,-128,0,0,4.7123894691467285]
    },
    "0-188356": {
      "deleted": false,
      "persistent": false,
      "initially_disabled": false,
      "blocked": false,
      "NAME": "Furn_De_R_Bookshelf_02",
      "DATA": [-460.2712097167969,-277.9642028808594,-47.63184356689453,0,0,4.71238899230957]
    },
    "0-188360": {
      "deleted": false,
      "persistent": false,
      "initially_disabled": false,
      "blocked": false,
      "NAME": "Furn_De_R_Bookshelf_02",
      "DATA": [-810.9275512695312,-288.9895935058594,-47.631813049316406,0,0,4.71238899230957]
    },
    "0-188364": {
      "deleted": false,
      "persistent": false,
      "initially_disabled": false,
      "blocked": false,
      "NAME": "furn_de_p_chair_02",
      "DATA": [235.4655303955078,-284.501220703125,-95.06617736816406,0,0,3.1415927410125732]
    },
    "0-188365": {
      "deleted": false,
      "persistent": false,
      "initially_disabled": false,
      "blocked": false,
      "NAME": "furn_de_p_chair_02",
      "DATA": [-246.95802307128906,-283.14215087890625,-95.06617736816406,0,0,3.1415927410125732]
    },
    "0-188366": {
      "deleted": false,
      "persistent": false,
      "initially_disabled": false,
      "blocked": false,
      "NAME": "furn_de_p_table_05",
      "DATA": [296.10638427734375,25.164836883544922,-96.97296142578125,0,0,0]
    },
    "0-188367": {
      "deleted": false,
      "persistent": false,
      "initially_disabled": false,
      "blocked": false,
      "NAME": "furn_de_p_chair_01",
      "DATA": [221.90719604492188,35.60759735107422,-90.6772232055664,0,0,4.71238899230957]
    },
    "0-188368": {
      "deleted": false,
      "persistent": false,
      "initially_disabled": false,
      "blocked": false,
      "NAME": "furn_de_p_chair_01",
      "DATA": [313.1569519042969,-72.57604217529297,-90.67723846435547,0,0,3.1415927410125732]
    },
    "0-241885": {
      "deleted": false,
      "persistent": false,
      "initially_disabled": false,
      "blocked": false,
      "NAME": "furn_de_rug_big_06",
      "XSCL": 1.3200000524520874,
      "DATA": [-636.635986328125,-293.2928466796875,-129.99867248535156,0,0,3.1415927410125732]
    },
    "0-241886": {
      "deleted": false,
      "persistent": false,
      "initially_disabled": false,
      "blocked": false,
      "NAME": "furn_de_p_bench_03",
      "DATA": [-222.15975952148438,53.17147445678711,-105.26107788085938,0,0,6.2831854820251465]
    },
    "0-281664": {
      "deleted": false,
      "persistent": false,
      "initially_disabled": false,
      "blocked": false,
      "NAME": "NorthMarker",
      "DATA": [599.6755981445312,-83.92190551757812,19.2633056640625,0,0,0]
    },
    "0-336869": {
      "deleted": false,
      "persistent": false,
      "initially_disabled": false,
      "blocked": false,
      "NAME": "light_de_lamp_04",
      "DATA": [-117.7363510131836,49.74213409423828,6.882110595703125,0,0,0]
    },
    "0-336870": {
      "deleted": false,
      "persistent": false,
      "initially_disabled": false,
      "blocked": false,
      "NAME": "furn_de_tapestry_03",
      "DATA": [-861.85498046875,-291.1481018066406,96.21355438232422,0,0,1.5707963705062866]
    },
    "0-336871": {
      "deleted": false,
      "persistent": false,
      "initially_disabled": false,
      "blocked": false,
      "NAME": "light_de_lamp_04",
      "DATA": [-546.4688110351562,-203.65585327148438,8.458481788635254,0,0,5.433185577392578]
    },
    "0-336872": {
      "deleted": false,
      "persistent": false,
      "initially_disabled": false,
      "blocked": false,
      "NAME": "furn_de_tapestry_03",
      "DATA": [-416.9098205566406,-284.6084899902344,96.21355438232422,0,0,4.71238899230957]
    },
    "0-336873": {
      "deleted": false,
      "persistent": false,
      "initially_disabled": false,
      "blocked": false,
      "NAME": "furn_de_tapestry_03",
      "DATA": [225.9788360595703,94.99796295166016,92.58946228027344,0,0,3.1415927410125732]
    },
    "0-336874": {
      "deleted": false,
      "persistent": false,
      "initially_disabled": false,
      "blocked": false,
      "NAME": "furn_de_tapestry_03",
      "DATA": [-227.10089111328125,95.29977416992188,92.58946228027344,0,0,3.1415927410125732]
    },
    "0-336875": {
      "deleted": false,
      "persistent": false,
      "initially_disabled": false,
      "blocked": false,
      "NAME": "furn_de_tapestry_03",
      "DATA": [352.8847351074219,-219.6461944580078,92.58946228027344,0,0,4.71238899230957]
    },
    "0-336876": {
      "deleted": false,
      "persistent": false,
      "initially_disabled": false,
      "blocked": false,
      "NAME": "furn_de_tapestry_03",
      "DATA": [225.97613525390625,-349.9377746582031,92.58946228027344,0,0,6.2831854820251465]
    },
    "0-336877": {
      "deleted": false,
      "persistent": false,
      "initially_disabled": false,
      "blocked": false,
      "NAME": "furn_de_tapestry_03",
      "DATA": [-351.02264404296875,-242.955078125,92.58946228027344,0,0,1.5707963705062866]
    },
    "0-336878": {
      "deleted": false,
      "persistent": false,
      "initially_disabled": false,
      "blocked": false,
      "NAME": "bk_InvocationOfAzura",
      "ANAM": "rathyne thirano",
      "INTV": 0,
      "NAM9": 1,
      "DATA": [-457.8294982910156,-209.19900512695312,1.2619999647140503,0,0,0]
    },
    "0-336879": {
      "deleted": false,
      "persistent": false,
      "initially_disabled": false,
      "blocked": false,
      "NAME": "bk_HomiliesOfBlessedAlmalexia",
      "ANAM": "rathyne thirano",
      "INTV": 0,
      "NAM9": 1,
      "DATA": [-458.19451904296875,-261.4219970703125,2.2100000381469727,0,0,0]
    },
    "0-336880": {
      "deleted": false,
      "persistent": false,
      "initially_disabled": false,
      "blocked": false,
      "NAME": "bk_graspingfortune",
      "ANAM": "rathyne thirano",
      "INTV": 0,
      "NAM9": 1,
      "DATA": [-465.1080322265625,-362.2510681152344,14.354927062988281,1.5707963705062866,0,0]
    },
    "0-336881": {
      "deleted": false,
      "persistent": false,
      "initially_disabled": false,
      "blocked": false,
      "NAME": "bk_frontierconquestaccommodat",
      "ANAM": "rathyne thirano",
      "INTV": 0,
      "NAM9": 1,
      "DATA": [-459.7927551269531,-356.2441101074219,17.754886627197266,1.5707963705062866,0,0]
    },
    "0-336882": {
      "deleted": false,
      "persistent": false,
      "initially_disabled": false,
      "blocked": false,
      "NAME": "bk_firmament",
      "ANAM": "rathyne thirano",
      "INTV": 0,
      "NAM9": 1,
      "DATA": [-464.4251403808594,-350.2851257324219,14.354925155639648,1.5707963705062866,0,0]
    },
    "0-336883": {
      "deleted": false,
      "persistent": false,
      "initially_disabled": false,
      "blocked": false,
      "NAME": "bk_easternprovincesimpartial",
      "ANAM": "rathyne thirano",
      "INTV": 0,
      "NAM9": 1,
      "DATA": [-460.3153076171875,-331.2618103027344,17.761356353759766,1.5707963705062866,0,0]
    },
    "0-336884": {
      "deleted": false,
      "persistent": false,
      "initially_disabled": false,
      "blocked": false,
      "NAME": "bk_easternprovincesimpartial",
      "ANAM": "rathyne thirano",
      "INTV": 0,
      "NAM9": 1,
      "DATA": [-460.3247375488281,-344.06549072265625,17.761356353759766,1.5707963705062866,0,0]
    },
    "0-336885": {
      "deleted": false,
      "persistent": false,
      "initially_disabled": false,
      "blocked": false,
      "NAME": "bk_easternprovincesimpartial",
      "ANAM": "rathyne thirano",
      "INTV": 0,
      "NAM9": 1,
      "DATA": [-460.15966796875,-337.62933349609375,17.761356353759766,1.5707963705062866,0,0]
    },
    "0-336886": {
      "deleted": false,
      "persistent": false,
      "initially_disabled": false,
      "blocked": false,
      "NAME": "bk_DoorsOfTheSpirit",
      "XSCL": 0.8300000429153442,
      "ANAM": "rathyne thirano",
      "INTV": 0,
      "NAM9": 1,
      "DATA": [-458.6222229003906,-294.9048767089844,-48.74254608154297,0,0,1.4707963466644287]
    },
    "0-336887": {
      "deleted": false,
      "persistent": false,
      "initially_disabled": false,
      "blocked": false,
      "NAME": "bk_darkestdarkness",
      "ANAM": "rathyne thirano",
      "INTV": 0,
      "NAM9": 1,
      "DATA": [-455.5158996582031,-222.70481872558594,-28.868074417114258,0,0,0.000000003725290298461914]
    },
    "0-336888": {
      "deleted": false,
      "persistent": false,
      "initially_disabled": false,
      "blocked": false,
      "NAME": "bk_darkestdarkness",
      "ANAM": "rathyne thirano",
      "INTV": 0,
      "NAM9": 1,
      "DATA": [-460.7648620605469,-220.94723510742188,-47.39639663696289,0,0,0]
    },
    "0-336889": {
      "deleted": false,
      "persistent": false,
      "initially_disabled": false,
      "blocked": false,
      "NAME": "bk_ConsolationsOfPrayer",
      "ANAM": "rathyne thirano",
      "INTV": 0,
      "NAM9": 1,
      "DATA": [-466.7383117675781,-314.11669921875,14.410432815551758,1.2217304706573486,0,0]
    },
    "0-336890": {
      "deleted": false,
      "persistent": false,
      "initially_disabled": false,
      "blocked": false,
      "NAME": "bk_ConsolationsOfPrayer",
      "ANAM": "rathyne thirano",
      "INTV": 0,
      "NAM9": 1,
      "DATA": [-467.2699279785156,-322.3944091796875,14.63271713256836,1.3962633609771729,0,0]
    },
    "0-336891": {
      "deleted": false,
      "persistent": false,
      "initially_disabled": false,
      "blocked": false,
      "NAME": "bk_darkestdarkness",
      "ANAM": "rathyne thirano",
      "INTV": 0,
      "NAM9": 1,
      "DATA": [-458.34674072265625,-222.82037353515625,-38.1327018737793,0,0,0.07500000298023224]
    },
    "0-336892": {
      "deleted": false,
      "persistent": false,
      "initially_disabled": false,
      "blocked": false,
      "NAME": "bk_ChroniclesNchuleft",
      "ANAM": "rathyne thirano",
      "INTV": 0,
      "NAM9": 1,
      "DATA": [-460.50390625,-203.51361083984375,-84.06655883789062,1.5707963705062866,0,0]
    },
    "0-336893": {
      "deleted": false,
      "persistent": false,
      "initially_disabled": false,
      "blocked": false,
      "NAME": "bk_ChroniclesNchuleft",
      "ANAM": "rathyne thirano",
      "INTV": 0,
      "NAM9": 1,
      "DATA": [-461.000732421875,-190.9121551513672,-84.06655883789062,1.5707963705062866,0,0]
    },
    "0-336894": {
      "deleted": false,
      "persistent": false,
      "initially_disabled": false,
      "blocked": false,
      "NAME": "bk_ChroniclesNchuleft",
      "ANAM": "rathyne thirano",
      "INTV": 0,
      "NAM9": 1,
      "DATA": [-460.6651611328125,-196.98739624023438,-84.06655883789062,1.5707963705062866,0,0]
    },
    "0-336895": {
      "deleted": false,
      "persistent": false,
      "initially_disabled": false,
      "blocked": false,
      "NAME": "bk_ChildrensAnuad",
      "ANAM": "rathyne thirano",
      "INTV": 0,
      "NAM9": 1,
      "DATA": [-458.7155456542969,-221.4949493408203,-84.06655883789062,1.5707963705062866,0,0]
    },
    "0-336896": {
      "deleted": false,
      "persistent": false,
      "initially_disabled": false,
      "blocked": false,
      "NAME": "bk_ChildrensAnuad",
      "ANAM": "rathyne thirano",
      "INTV": 0,
      "NAM9": 1,
      "DATA": [-457.5555419921875,-209.90960693359375,-84.06655883789062,1.5707963705062866,0,0]
    },
    "0-336897": {
      "deleted": false,
      "persistent": false,
      "initially_disabled": false,
      "blocked": false,
      "NAME": "bk_ChildrensAnuad",
      "ANAM": "rathyne thirano",
      "INTV": 0,
      "NAM9": 1,
      "DATA": [-458.507080078125,-215.877685546875,-84.06655883789062,1.5707963705062866,0,0]
    },
    "0-336898": {
      "deleted": false,
      "persistent": false,
      "initially_disabled": false,
      "blocked": false,
      "NAME": "bk_ChildrenOfTheSky",
      "ANAM": "rathyne thirano",
      "INTV": 0,
      "NAM9": 1,
      "DATA": [-460.66650390625,-241.86270141601562,-91.06150817871094,0,0,6.258185386657715]
    },
    "0-336899": {
      "deleted": false,
      "persistent": false,
      "initially_disabled": false,
      "blocked": false,
      "NAME": "bk_ChildrenOfTheSky",
      "ANAM": "rathyne thirano",
      "INTV": 0,
      "NAM9": 1,
      "DATA": [-460.6372985839844,-241.12261962890625,-97.06170654296875,0,0,0]
    },
    "0-336900": {
      "deleted": false,
      "persistent": false,
      "initially_disabled": false,
      "blocked": false,
      "NAME": "bk_BriefHistoryEmpire4",
      "ANAM": "rathyne thirano",
      "INTV": 0,
      "NAM9": 1,
      "DATA": [-465.1158752441406,-290.298828125,-84.83991241455078,0,0,6.258185386657715]
    },
    "0-336901": {
      "deleted": false,
      "persistent": false,
      "initially_disabled": false,
      "blocked": false,
      "NAME": "bk_BriefHistoryEmpire4",
      "ANAM": "rathyne thirano",
      "INTV": 0,
      "NAM9": 1,
      "DATA": [-465.8393249511719,-289.9542541503906,-96.10379028320312,0,0,0]
    },
    "0-336902": {
      "deleted": false,
      "persistent": false,
      "initially_disabled": false,
      "blocked": false,
      "NAME": "bk_BriefHistoryEmpire4",
      "ANAM": "rathyne thirano",
      "INTV": 0,
      "NAM9": 1,
      "DATA": [-465.8393249511719,-289.9542541503906,-90.84791564941406,0,0,6.258185386657715]
    },
    "0-336903": {
      "deleted": false,
      "persistent": false,
      "initially_disabled": false,
      "blocked": false,
      "NAME": "bk_BriefHistoryEmpire2",
      "ANAM": "rathyne thirano",
      "INTV": 0,
      "NAM9": 1,
      "DATA": [-456.5477600097656,-343.0199279785156,-86.12646484375,0,0,0.04999971389770508]
    },
    "0-336904": {
      "deleted": false,
      "persistent": false,
      "initially_disabled": false,
      "blocked": false,
      "NAME": "bk_BriefHistoryEmpire2",
      "ANAM": "rathyne thirano",
      "INTV": 0,
      "NAM9": 1,
      "DATA": [-458.4952697753906,-342.9244689941406,-97.06170654296875,0,0,0]
    },
    "0-336905": {
      "deleted": false,
      "persistent": false,
      "initially_disabled": false,
      "blocked": false,
      "NAME": "bk_BriefHistoryEmpire2",
      "ANAM": "rathyne thirano",
      "INTV": 0,
      "NAM9": 1,
      "DATA": [-458.4955139160156,-342.92401123046875,-91.80650329589844,0,0,6.208185195922852]
    },
    "0-336906": {
      "deleted": false,
      "persistent": false,
      "initially_disabled": false,
      "blocked": false,
      "NAME": "furn_de_tapestry_03",
      "DATA": [-9.044561386108398,-605.043212890625,96.21355438232422,0,0,0]
    },
    "0-336907": {
      "deleted": false,
      "persistent": false,
      "initially_disabled": false,
      "blocked": false,
      "NAME": "furn_de_tapestry_03",
      "DATA": [-863.635498046875,-495.3370666503906,96.21355438232422,0,0,1.5707963705062866]
    },
    "0-336908": {
      "deleted": false,
      "persistent": false,
      "initially_disabled": false,
      "blocked": false,
      "NAME": "furn_de_tapestry_03",
      "DATA": [-365.46954345703125,-605.043212890625,96.21355438232422,0,0,0]
    },
    "0-336909": {
      "deleted": false,
      "persistent": false,
      "initially_disabled": false,
      "blocked": false,
      "NAME": "bk_BriefHistoryEmpire3",
      "ANAM": "rathyne thirano",
      "INTV": 0,
      "NAM9": 1,
      "DATA": [-816.2517700195312,-352.2726745605469,-85.79686737060547,0,0,3.166592597961426]
    },
    "0-336910": {
      "deleted": false,
      "persistent": false,
      "initially_disabled": false,
      "blocked": false,
      "NAME": "bk_BriefHistoryEmpire3",
      "ANAM": "rathyne thirano",
      "INTV": 0,
      "NAM9": 1,
      "DATA": [-812.43896484375,-352.322998046875,-97.06167602539062,0,0,3.1415927410125732]
    },
    "0-336911": {
      "deleted": false,
      "persistent": false,
      "initially_disabled": false,
      "blocked": false,
      "NAME": "bk_BriefHistoryEmpire3",
      "ANAM": "rathyne thirano",
      "INTV": 0,
      "NAM9": 1,
      "DATA": [-814.0817260742188,-351.75653076171875,-91.80670928955078,0,0,3.216592788696289]
    },
    "0-336912": {
      "deleted": false,
      "persistent": false,
      "initially_disabled": false,
      "blocked": false,
      "NAME": "bk_BriefHistoryEmpire1",
      "ANAM": "rathyne thirano",
      "INTV": 0,
      "NAM9": 1,
      "DATA": [-813.7890625,-301.12994384765625,-85.79861450195312,0,0,3.174999952316284]
    },
    "0-336913": {
      "deleted": false,
      "persistent": false,
      "initially_disabled": false,
      "blocked": false,
      "NAME": "bk_BriefHistoryEmpire1",
      "ANAM": "rathyne thirano",
      "INTV": 0,
      "NAM9": 1,
      "DATA": [-813.27099609375,-302.7421569824219,-97.06167602539062,0,0,3.0999999046325684]
    },
    "0-336914": {
      "deleted": false,
      "persistent": false,
      "initially_disabled": false,
      "blocked": false,
      "NAME": "bk_BriefHistoryEmpire1",
      "ANAM": "rathyne thirano",
      "INTV": 0,
      "NAM9": 1,
      "DATA": [-813.27099609375,-302.7421569824219,-91.80670928955078,0,0,3.174999952316284]
    },
    "0-336920": {
      "deleted": false,
      "persistent": false,
      "initially_disabled": false,
      "blocked": false,
      "NAME": "bk_BlasphemousRevenants",
      "ANAM": "rathyne thirano",
      "INTV": 0,
      "NAM9": 1,
      "DATA": [-808.7176513671875,-344.08990478515625,-48.081214904785156,0,0,0]
    },
    "0-336921": {
      "deleted": false,
      "persistent": false,
      "initially_disabled": false,
      "blocked": false,
      "NAME": "bk_BiographyBarenziah3",
      "ANAM": "rathyne thirano",
      "INTV": 0,
      "NAM9": 1,
      "DATA": [-811.9222412109375,-203.83480834960938,-32.529441833496094,4.71238899230957,3.133185386657715,0]
    },
    "0-336922": {
      "deleted": false,
      "persistent": false,
      "initially_disabled": false,
      "blocked": false,
      "NAME": "bk_BiographyBarenziah2",
      "ANAM": "rathyne thirano",
      "INTV": 0,
      "NAM9": 1,
      "DATA": [-813.4188232421875,-229.06866455078125,-49.02891540527344,0,0,3.0250003337860107]
    },
    "0-336923": {
      "deleted": false,
      "persistent": false,
      "initially_disabled": false,
      "blocked": false,
      "NAME": "bk_BiographyBarenziah1",
      "ANAM": "rathyne thirano",
      "INTV": 0,
      "NAM9": 1,
      "DATA": [-815.7918701171875,-228.697265625,-43.77686309814453,0,0,6.258185386657715]
    },
    "0-336924": {
      "deleted": false,
      "persistent": false,
      "initially_disabled": false,
      "blocked": false,
      "NAME": "bk_ArcturianHeresy",
      "ANAM": "rathyne thirano",
      "INTV": 0,
      "NAM9": 1,
      "DATA": [-809.48388671875,-286.6929931640625,-49.025001525878906,0,0,4.583234786987305]
    },
    "0-336925": {
      "deleted": false,
      "persistent": false,
      "initially_disabled": false,
      "blocked": false,
      "NAME": "bk_ArcturianHeresy",
      "ANAM": "rathyne thirano",
      "INTV": 0,
      "NAM9": 1,
      "DATA": [-809.4835205078125,-286.6932373046875,-43.769309997558594,0,0,4.508185863494873]
    },
    "0-336926": {
      "deleted": false,
      "persistent": false,
      "initially_disabled": false,
      "blocked": false,
      "NAME": "bk_ArcanaRestored",
      "ANAM": "rathyne thirano",
      "INTV": 0,
      "NAM9": 1,
      "DATA": [-810.8444213867188,-366.34454345703125,22.0024471282959,1.5707963705062866,3.1415927410125732,0]
    },
    "0-336927": {
      "deleted": false,
      "persistent": false,
      "initially_disabled": false,
      "blocked": false,
      "NAME": "bk_ArcanaRestored",
      "ANAM": "rathyne thirano",
      "INTV": 0,
      "NAM9": 1,
      "DATA": [-810.31689453125,-372.630615234375,22.0024471282959,1.5707963705062866,3.1415927410125732,0]
    },
    "0-336928": {
      "deleted": false,
      "persistent": false,
      "initially_disabled": false,
      "blocked": false,
      "NAME": "bk_Anticipations",
      "ANAM": "rathyne thirano",
      "INTV": 0,
      "NAM9": 1,
      "DATA": [-814.438232421875,-330.35113525390625,15.254888534545898,4.720797538757324,3.1415927410125732,0]
    },
    "0-336929": {
      "deleted": false,
      "persistent": false,
      "initially_disabled": false,
      "blocked": false,
      "NAME": "bk_Anticipations",
      "ANAM": "rathyne thirano",
      "INTV": 0,
      "NAM9": 1,
      "DATA": [-812.8499755859375,-360.7060546875,15.254888534545898,4.720797538757324,3.1415927410125732,0]
    },
    "0-336930": {
      "deleted": false,
      "persistent": false,
      "initially_disabled": false,
      "blocked": false,
      "NAME": "bk_Anticipations",
      "ANAM": "rathyne thirano",
      "INTV": 0,
      "NAM9": 1,
      "DATA": [-813.7754516601562,-354.5313720703125,15.254888534545898,4.720797538757324,3.1415927410125732,0]
    },
    "0-336931": {
      "deleted": false,
      "persistent": false,
      "initially_disabled": false,
      "blocked": false,
      "NAME": "bk_Anticipations",
      "ANAM": "rathyne thirano",
      "INTV": 0,
      "NAM9": 1,
      "DATA": [-814.4348754882812,-348.6943359375,15.254888534545898,4.720797538757324,3.1415927410125732,0]
    },
    "0-336932": {
      "deleted": false,
      "persistent": false,
      "initially_disabled": false,
      "blocked": false,
      "NAME": "bk_Anticipations",
      "ANAM": "rathyne thirano",
      "INTV": 0,
      "NAM9": 1,
      "DATA": [-814.5612182617188,-342.10980224609375,15.254888534545898,4.720797538757324,3.1415927410125732,0]
    },
    "0-336933": {
      "deleted": false,
      "persistent": false,
      "initially_disabled": false,
      "blocked": false,
      "NAME": "bk_Anticipations",
      "ANAM": "rathyne thirano",
      "INTV": 0,
      "NAM9": 1,
      "DATA": [-814.6720581054688,-336.22918701171875,15.254888534545898,4.720797538757324,3.1415927410125732,0]
    },
    "0-336934": {
      "deleted": false,
      "persistent": false,
      "initially_disabled": false,
      "blocked": false,
      "NAME": "bk_AntecedantsDwemerLaw",
      "ANAM": "rathyne thirano",
      "INTV": 0,
      "NAM9": 1,
      "DATA": [-814.5098876953125,-298.38299560546875,7.26200008392334,0,0,3.1241393089294434]
    },
    "0-336935": {
      "deleted": false,
      "persistent": false,
      "initially_disabled": false,
      "blocked": false,
      "NAME": "bk_AntecedantsDwemerLaw",
      "ANAM": "rathyne thirano",
      "INTV": 0,
      "NAM9": 1,
      "DATA": [-814.5098876953125,-298.3834228515625,1.2618904113769531,0,0,6.208185195922852]
    },
    "0-336936": {
      "deleted": false,
      "persistent": false,
      "initially_disabled": false,
      "blocked": false,
      "NAME": "bk_AnnotatedAnuad",
      "ANAM": "rathyne thirano",
      "INTV": 0,
      "NAM9": 1,
      "DATA": [-811.0531005859375,-256.1712646484375,6.502117156982422,0,0,4.483185768127441]
    },
    "0-336937": {
      "deleted": false,
      "persistent": false,
      "initially_disabled": false,
      "blocked": false,
      "NAME": "bk_AnnotatedAnuad",
      "ANAM": "rathyne thirano",
      "INTV": 0,
      "NAM9": 1,
      "DATA": [-811.0531005859375,-256.1712646484375,1.2619056701660156,0,0,4.58318567276001]
    },
    "0-336938": {
      "deleted": false,
      "persistent": false,
      "initially_disabled": false,
      "blocked": false,
      "NAME": "bk_AffairsOfWizards",
      "ANAM": "rathyne thirano",
      "INTV": 0,
      "NAM9": 1,
      "DATA": [-816.5682983398438,-255.49424743652344,12.507755279541016,0,0,4.558186054229736]
    },
    "0-336939": {
      "deleted": false,
      "persistent": false,
      "initially_disabled": false,
      "blocked": false,
      "NAME": "bk_AedraAndDaedra",
      "ANAM": "rathyne thirano",
      "INTV": 0,
      "NAM9": 1,
      "DATA": [-811.9028930664062,-218.82699584960938,1.2660000324249268,0,0,4.658283710479736]
    },
    "0-336940": {
      "deleted": false,
      "persistent": false,
      "initially_disabled": false,
      "blocked": false,
      "NAME": "bk_AedraAndDaedra",
      "ANAM": "rathyne thirano",
      "INTV": 0,
      "NAM9": 1,
      "DATA": [-811.9026489257812,-218.82704162597656,12.521986961364746,0,0,4.633185863494873]
    },
    "0-336941": {
      "deleted": false,
      "persistent": false,
      "initially_disabled": false,
      "blocked": false,
      "NAME": "bk_AedraAndDaedra",
      "ANAM": "rathyne thirano",
      "INTV": 0,
      "NAM9": 1,
      "DATA": [-811.9026489257812,-218.82704162597656,6.521987438201904,0,0,4.633185863494873]
    },
    "0-336942": {
      "deleted": false,
      "persistent": false,
      "initially_disabled": false,
      "blocked": false,
      "NAME": "furn_de_rug_big_06",
      "XSCL": 2,
      "DATA": [-12.862964630126953,-143.84075927734375,-132.7708282470703,0,0,3.1415927410125732]
    },
    "0-405541": {
      "deleted": false,
      "persistent": false,
      "initially_disabled": false,
      "blocked": false,
      "NAME": "Gold_025",
      "DATA": [244.44131469726562,-194.36253356933594,-58.66313552856445,0,0,1.1000007390975952]
    },
    "0-405542": {
      "deleted": false,
      "persistent": false,
      "initially_disabled": false,
      "blocked": false,
      "NAME": "Gold_001",
      "DATA": [235.16189575195312,-194.48904418945312,-58.74374771118164,0,0,4.783186435699463]
    },
    "0-405543": {
      "deleted": false,
      "persistent": false,
      "initially_disabled": false,
      "blocked": false,
      "NAME": "Gold_005",
      "DATA": [231.9386444091797,-188.6401824951172,-58.832305908203125,0,0,3.6831858158111572]
    },
    "0-188354": {
      "deleted": false,
      "persistent": false,
      "initially_disabled": false,
      "blocked": false,
      "NAME": "in_velothismall_ndoor_01",
      "DATA": [64,-384,-128,0,0,1.5707963705062866]
    },
    "0-423146": {
      "deleted": false,
      "persistent": false,
      "initially_disabled": false,
      "blocked": false,
      "NAME": "sc_paper plain",
      "ANAM": "rathyne thirano",
      "INTV": 0,
      "NAM9": 1,
      "DATA": [198.90977478027344,-207.9040069580078,-58.04071044921875,0,0,5.097787380218506]
    },
    "0-423147": {
      "deleted": false,
      "persistent": false,
      "initially_disabled": false,
      "blocked": false,
      "NAME": "Misc_Quill",
      "ANAM": "rathyne thirano",
      "INTV": 0,
      "NAM9": 1,
      "DATA": [215.41477966308594,-211.3699188232422,-57.67759323120117,0,0,0.4000000059604645]
    },
    "0-423148": {
      "deleted": false,
      "persistent": false,
      "initially_disabled": false,
      "blocked": false,
      "NAME": "Misc_Inkwell",
      "ANAM": "rathyne thirano",
      "INTV": 0,
      "NAM9": 1,
      "DATA": [198.99818420410156,-207.76004028320312,-52.2403678894043,0,0,0]
    },
    "0-423149": {
      "deleted": false,
      "persistent": false,
      "initially_disabled": false,
      "blocked": false,
      "NAME": "furn_de_tapestry_03",
      "DATA": [-351.02264404296875,-21.743526458740234,92.58946228027344,0,0,1.5707963705062866]
    },
    "0-423150": {
      "deleted": false,
      "persistent": false,
      "initially_disabled": false,
      "blocked": false,
      "NAME": "furn_de_tapestry_03",
      "DATA": [352.8847351074219,-18.821300506591797,92.58946228027344,0,0,4.71238899230957]
    },
    "0-423151": {
      "deleted": false,
      "persistent": false,
      "initially_disabled": false,
      "blocked": false,
      "NAME": "furn_de_tapestry_03",
      "DATA": [-549.5259399414062,-605.043212890625,96.21355438232422,0,0,0]
    },
    "0-423152": {
      "deleted": false,
      "persistent": false,
      "initially_disabled": false,
      "blocked": false,
      "NAME": "furn_de_tapestry_03",
      "DATA": [-731.2394409179688,-605.043212890625,96.21355438232422,0,0,0]
    },
    "0-423153": {
      "deleted": false,
      "persistent": false,
      "initially_disabled": false,
      "blocked": false,
      "NAME": "furn_de_tapestry_03",
      "DATA": [-183.75604248046875,-605.043212890625,96.21355438232422,0,0,0]
    },
    "0-423154": {
      "deleted": false,
      "persistent": false,
      "initially_disabled": false,
      "blocked": false,
      "NAME": "furn_planter_02",
      "XSCL": 0.5,
      "DATA": [-304.480712890625,-123.07258605957031,-127.9999771118164,0,0,0]
    },
    "0-423155": {
      "deleted": false,
      "persistent": false,
      "initially_disabled": false,
      "blocked": false,
      "NAME": "flora_grass_01",
      "XSCL": 1.350000023841858,
      "DATA": [-303.4606018066406,-122.68699645996094,-68.96199798583984,0,0,0]
    },
    "0-423156": {
      "deleted": false,
      "persistent": false,
      "initially_disabled": false,
      "blocked": false,
      "NAME": "bk_InvocationOfAzura",
      "ANAM": "rathyne thirano",
      "INTV": 0,
      "NAM9": 1,
      "DATA": [-642.3717651367188,-351.182861328125,-34.17146301269531,4.71238899230957,0,0]
    },
    "0-423157": {
      "deleted": false,
      "persistent": false,
      "initially_disabled": false,
      "blocked": false,
      "NAME": "bk_firmament",
      "ANAM": "rathyne thirano",
      "INTV": 0,
      "NAM9": 1,
      "DATA": [-651.719970703125,-252.36656188964844,16.11933708190918,4.71238899230957,0,0]
    },
    "0-423158": {
      "deleted": false,
      "persistent": false,
      "initially_disabled": false,
      "blocked": false,
      "NAME": "bk_InvocationOfAzura",
      "ANAM": "rathyne thirano",
      "INTV": 0,
      "NAM9": 1,
      "DATA": [-643.3883056640625,-345.175537109375,-34.17146301269531,4.71238899230957,0,0]
    },
    "0-423159": {
      "deleted": false,
      "persistent": false,
      "initially_disabled": false,
      "blocked": false,
      "NAME": "bk_reflectionsoncultworship...",
      "ANAM": "rathyne thirano",
      "INTV": 0,
      "NAM9": 1,
      "DATA": [-643.0462646484375,-289.236572265625,19.51930046081543,4.71238899230957,0,0]
    },
    "0-423160": {
      "deleted": false,
      "persistent": false,
      "initially_disabled": false,
      "blocked": false,
      "NAME": "bk_firmament",
      "ANAM": "rathyne thirano",
      "INTV": 0,
      "NAM9": 1,
      "DATA": [-651.884521484375,-233.87255859375,16.119367599487305,4.312389373779297,0,0]
    },
    "0-423161": {
      "deleted": false,
      "persistent": false,
      "initially_disabled": false,
      "blocked": false,
      "NAME": "bk_firmament",
      "ANAM": "rathyne thirano",
      "INTV": 0,
      "NAM9": 1,
      "DATA": [-654.3204345703125,-246.13003540039062,16.11933708190918,4.71238899230957,0,0]
    },
    "0-423162": {
      "deleted": false,
      "persistent": false,
      "initially_disabled": false,
      "blocked": false,
      "NAME": "bk_firmament",
      "ANAM": "rathyne thirano",
      "INTV": 0,
      "NAM9": 1,
      "DATA": [-656.3912353515625,-258.5107727050781,16.11933708190918,4.71238899230957,0,0]
    },
    "0-423163": {
      "deleted": false,
      "persistent": false,
      "initially_disabled": false,
      "blocked": false,
      "NAME": "bk_reflectionsoncultworship...",
      "ANAM": "rathyne thirano",
      "INTV": 0,
      "NAM9": 1,
      "DATA": [-643.6000366210938,-264.5718078613281,19.51930046081543,4.71238899230957,0,0]
    },
    "0-423164": {
      "deleted": false,
      "persistent": false,
      "initially_disabled": false,
      "blocked": false,
      "NAME": "bk_reflectionsoncultworship...",
      "ANAM": "rathyne thirano",
      "INTV": 0,
      "NAM9": 1,
      "DATA": [-644.7767944335938,-270.6527404785156,19.51930046081543,4.71238899230957,0,0]
    },
    "0-423165": {
      "deleted": false,
      "persistent": false,
      "initially_disabled": false,
      "blocked": false,
      "NAME": "bk_reflectionsoncultworship...",
      "ANAM": "rathyne thirano",
      "INTV": 0,
      "NAM9": 1,
      "DATA": [-643.32861328125,-276.8626708984375,19.51930046081543,4.71238899230957,0,0]
    },
    "0-423166": {
      "deleted": false,
      "persistent": false,
      "initially_disabled": false,
      "blocked": false,
      "NAME": "bk_reflectionsoncultworship...",
      "ANAM": "rathyne thirano",
      "INTV": 0,
      "NAM9": 1,
      "DATA": [-644.5134887695312,-282.9659423828125,19.51930046081543,4.71238899230957,0,0]
    },
    "0-423172": {
      "deleted": false,
      "persistent": false,
      "initially_disabled": false,
      "blocked": false,
      "NAME": "bk_InvocationOfAzura",
      "ANAM": "rathyne thirano",
      "INTV": 0,
      "NAM9": 1,
      "DATA": [-644.8973388671875,-370.212158203125,-34.17146301269531,4.71238899230957,0,0]
    },
    "0-423173": {
      "deleted": false,
      "persistent": false,
      "initially_disabled": false,
      "blocked": false,
      "NAME": "bk_InvocationOfAzura",
      "ANAM": "rathyne thirano",
      "INTV": 0,
      "NAM9": 1,
      "DATA": [-642.6490478515625,-363.6806640625,-34.17146301269531,4.71238899230957,0,0]
    },
    "0-423174": {
      "deleted": false,
      "persistent": false,
      "initially_disabled": false,
      "blocked": false,
      "NAME": "bk_InvocationOfAzura",
      "ANAM": "rathyne thirano",
      "INTV": 0,
      "NAM9": 1,
      "DATA": [-644.6130981445312,-357.382568359375,-34.17146301269531,4.71238899230957,0,0]
    },
    "0-423175": {
      "deleted": false,
      "persistent": false,
      "initially_disabled": false,
      "blocked": false,
      "NAME": "bk_vivecandmephala",
      "ANAM": "rathyne thirano",
      "INTV": 0,
      "NAM9": 1,
      "DATA": [-641.318115234375,-307.595947265625,-30.771533966064453,4.71238899230957,0,6.2831854820251465]
    },
    "0-423176": {
      "deleted": false,
      "persistent": false,
      "initially_disabled": false,
      "blocked": false,
      "NAME": "bk_vivecandmephala",
      "ANAM": "rathyne thirano",
      "INTV": 0,
      "NAM9": 1,
      "DATA": [-641.9928588867188,-339.117431640625,-30.771533966064453,4.71238899230957,0,6.2831854820251465]
    },
    "0-423177": {
      "deleted": false,
      "persistent": false,
      "initially_disabled": false,
      "blocked": false,
      "NAME": "bk_vivecandmephala",
      "ANAM": "rathyne thirano",
      "INTV": 0,
      "NAM9": 1,
      "DATA": [-643.21533203125,-332.681884765625,-30.771533966064453,4.71238899230957,0,6.2831854820251465]
    },
    "0-423178": {
      "deleted": false,
      "persistent": false,
      "initially_disabled": false,
      "blocked": false,
      "NAME": "bk_vivecandmephala",
      "ANAM": "rathyne thirano",
      "INTV": 0,
      "NAM9": 1,
      "DATA": [-644.4790649414062,-326.301025390625,-30.771533966064453,4.71238899230957,0,6.2831854820251465]
    },
    "0-423179": {
      "deleted": false,
      "persistent": false,
      "initially_disabled": false,
      "blocked": false,
      "NAME": "bk_vivecandmephala",
      "ANAM": "rathyne thirano",
      "INTV": 0,
      "NAM9": 1,
      "DATA": [-642.6383666992188,-320.25537109375,-30.771533966064453,4.71238899230957,0,6.2831854820251465]
    },
    "0-423180": {
      "deleted": false,
      "persistent": false,
      "initially_disabled": false,
      "blocked": false,
      "NAME": "bk_vivecandmephala",
      "ANAM": "rathyne thirano",
      "INTV": 0,
      "NAM9": 1,
      "DATA": [-645.258056640625,-314.138427734375,-30.771533966064453,4.71238899230957,0,6.2831854820251465]
    },
    "0-423182": {
      "deleted": false,
      "persistent": false,
      "initially_disabled": false,
      "blocked": false,
      "NAME": "bk_SaryonisSermons",
      "ANAM": "rathyne thirano",
      "INTV": 0,
      "NAM9": 1,
      "DATA": [-643.5575561523438,-321.8565368652344,4.65235710144043,0,0,0]
    },
    "0-423183": {
      "deleted": false,
      "persistent": false,
      "initially_disabled": false,
      "blocked": false,
      "NAME": "bk_HouseOfTroubles_c",
      "ANAM": "rathyne thirano",
      "INTV": 0,
      "NAM9": 1,
      "DATA": [-638.4915161132812,-202.14474487304688,-33.2714729309082,4.71238899230957,0,6.2831854820251465]
    },
    "0-423184": {
      "deleted": false,
      "persistent": false,
      "initially_disabled": false,
      "blocked": false,
      "NAME": "bk_HouseOfTroubles_c",
      "ANAM": "rathyne thirano",
      "INTV": 0,
      "NAM9": 1,
      "DATA": [-638.7190551757812,-208.18038940429688,-33.2714729309082,4.71238899230957,0,6.2831854820251465]
    },
    "0-423185": {
      "deleted": false,
      "persistent": false,
      "initially_disabled": false,
      "blocked": false,
      "NAME": "bk_HouseOfTroubles_c",
      "ANAM": "rathyne thirano",
      "INTV": 0,
      "NAM9": 1,
      "DATA": [-640.6903686523438,-214.21176147460938,-33.2714729309082,4.71238899230957,0,6.2831854820251465]
    },
    "0-423186": {
      "deleted": false,
      "persistent": false,
      "initially_disabled": false,
      "blocked": false,
      "NAME": "bk_HouseOfTroubles_c",
      "ANAM": "rathyne thirano",
      "INTV": 0,
      "NAM9": 1,
      "DATA": [-641.0327758789062,-220.38302612304688,-33.2714729309082,4.71238899230957,0,6.2831854820251465]
    },
    "0-423187": {
      "deleted": false,
      "persistent": false,
      "initially_disabled": false,
      "blocked": false,
      "NAME": "bk_HouseOfTroubles_c",
      "ANAM": "rathyne thirano",
      "INTV": 0,
      "NAM9": 1,
      "DATA": [-641.828125,-226.33566284179688,-33.2714729309082,4.71238899230957,0,6.2831854820251465]
    },
    "0-423188": {
      "deleted": false,
      "persistent": false,
      "initially_disabled": false,
      "blocked": false,
      "NAME": "bk_SaryonisSermons",
      "ANAM": "rathyne thirano",
      "INTV": 0,
      "NAM9": 1,
      "DATA": [-639.1937255859375,-317.8165588378906,-93.67506408691406,0,0,0]
    },
    "0-423189": {
      "deleted": false,
      "persistent": false,
      "initially_disabled": false,
      "blocked": false,
      "NAME": "bk_vivecandmephala",
      "ANAM": "rathyne thirano",
      "INTV": 0,
      "NAM9": 1,
      "DATA": [-639.68896484375,-322.3826904296875,-86.03758239746094,0,0,5.4977874755859375]
    },
    "0-423190": {
      "deleted": false,
      "persistent": false,
      "initially_disabled": false,
      "blocked": false,
      "NAME": "bk_RealBarenziah1",
      "ANAM": "rathyne thirano",
      "INTV": 0,
      "NAM9": 1,
      "DATA": [-644.3212890625,-229.13839721679688,-89.29695129394531,0,0,0]
    },
    "0-423191": {
      "deleted": false,
      "persistent": false,
      "initially_disabled": false,
      "blocked": false,
      "NAME": "bk_RealBarenziah1",
      "ANAM": "rathyne thirano",
      "INTV": 0,
      "NAM9": 1,
      "DATA": [-645.5180053710938,-234.28659057617188,-95.30805969238281,0,0,0]
    },
    "0-423192": {
      "deleted": false,
      "persistent": false,
      "initially_disabled": false,
      "blocked": false,
      "NAME": "bk_realbarenziah3",
      "ANAM": "rathyne thirano",
      "INTV": 0,
      "NAM9": 1,
      "DATA": [-644.7353515625,-236.12521362304688,-83.29063415527344,0,0,5.883185863494873]
    },
    "0-423193": {
      "deleted": false,
      "persistent": false,
      "initially_disabled": false,
      "blocked": false,
      "NAME": "Furn_De_R_Bookshelf_02",
      "DATA": [-640.87451171875,-286.9324951171875,-45.8738899230957,0,0,4.71238899230957]
    },
    "0-423195": {
      "deleted": false,
      "persistent": false,
      "initially_disabled": false,
      "blocked": false,
      "NAME": "furn_planter_01",
      "XSCL": 0.5,
      "DATA": [-645.2830810546875,-259.0044860839844,-50.274749755859375,0,0,0]
    },
    "0-423196": {
      "deleted": false,
      "persistent": false,
      "initially_disabled": false,
      "blocked": false,
      "NAME": "flora_bc_grass_02",
      "XSCL": 0.5,
      "DATA": [-644.1121215820312,-258.9486389160156,-24.50006675720215,0,0,0]
    },
    "0-423197": {
      "deleted": false,
      "persistent": false,
      "initially_disabled": false,
      "blocked": false,
      "NAME": "flora_bc_grass_02",
      "XSCL": 0.5,
      "DATA": [-644.1121215820312,-258.9486389160156,-24.50006675720215,0,0,1.3000000715255737]
    },
    "0-423198": {
      "deleted": false,
      "persistent": false,
      "initially_disabled": false,
      "blocked": false,
      "NAME": "light_de_lantern_03_200",
      "XSCL": 1.190000057220459,
      "DATA": [-11.042399406433105,-497.5486145019531,99.06124114990234,0,0,0.7853981852531433]
    },
    "0-423199": {
      "deleted": false,
      "persistent": false,
      "initially_disabled": false,
      "blocked": false,
      "NAME": "furn_de_rope_03",
      "DATA": [-7.334277153015137,-500.4668273925781,118.71084594726562,0,0,0]
    },
    "0-423200": {
      "deleted": false,
      "persistent": false,
      "initially_disabled": false,
      "blocked": false,
      "NAME": "furn_de_tapestry_03",
      "DATA": [-546.9742431640625,-159.4163818359375,96.21355438232422,0,0,3.1415927410125732]
    },
    "0-423201": {
      "deleted": false,
      "persistent": false,
      "initially_disabled": false,
      "blocked": false,
      "NAME": "furn_de_tapestry_03",
      "DATA": [-733.9078369140625,-159.4163818359375,96.21355438232422,0,0,3.1415927410125732]
    },
    "0-423202": {
      "deleted": false,
      "persistent": false,
      "initially_disabled": false,
      "blocked": false,
      "NAME": "bk_HomiliesOfBlessedAlmalexia",
      "ANAM": "rathyne thirano",
      "INTV": 0,
      "NAM9": 1,
      "DATA": [-247.85641479492188,-205.2002716064453,-53.5850715637207,0,0,1.4707963466644287]
    }
  }
}